sauron/__init__.py
sauron/engine.py
sauron/exporters.py
sauron/models.py
sauron/parsers.py
sauron/rule_engine.py
sauron_rule_engine/__init__.py
sauron_rule_engine/models.py
sauron_rule_engine/rule_engine.py
sauron_rule_engine-1.0.4.dist-info/LICENSE.txt
sauron_rule_engine-1.0.4.dist-info/WHEEL
sauron_rule_engine-1.0.4.dist-info/METADATA
sauron_rule_engine-1.0.4.dist-info/RECORD
