Metadata-Version: 2.1
Name: sauron-rule-engine
Version: 1.0.4
Summary: A simple rule engine implemented in python
Home-page: https://github.com/jlugao/sauron-rule-engine
License: MIT
Author: jlugao
Author-email: joaolhullier@gmail.com
Requires-Python: >=3.6,<4.0
Classifier: License :: OSI Approved :: MIT License
Classifier: Programming Language :: Python :: 3
Classifier: Programming Language :: Python :: 3.6
Classifier: Programming Language :: Python :: 3.7
Requires-Dist: mypy (>=0.711.0,<0.712.0)
Requires-Dist: pydantic (>=0.29.0,<0.30.0)
Requires-Dist: ruamel.yaml (>=0.16.5,<0.17.0)
Project-URL: Repository, https://github.com/jlugao/sauron-rule-engine
